[
  {
    "id": "konga",
    "name": "Konga",
    "logo": "/images/company-logos/konga.svg",
    "location": "Nigeria",
    "gradient": "from-blue-500/10 to-blue-600/10",
    "description": "Konga is a leading company providing excellent career opportunities.",
    "industry": "Various",
    "size": "Multiple employees",
    "website": "https://konga.com",
    "founded": "N/A",
    "specialties": [],
    "jobCount": 9
  },
  {
    "id": "fairmoney",
    "name": "FairMoney",
    "logo": "/images/company-logos/fairmoney.svg",
    "location": "Nigeria",
    "gradient": "from-blue-500/10 to-blue-600/10",
    "description": "FairMoney is a leading company providing excellent career opportunities.",
    "industry": "Various",
    "size": "Multiple employees",
    "website": "https://fairmoney.com",
    "founded": "N/A",
    "specialties": [],
    "jobCount": 8
  },
  {
    "id": "nestle-nigeria",
    "name": "Nestle Nigeria",
    "logo": "/images/company-logos/nestle-nigeria.svg",
    "location": "Nigeria",
    "gradient": "from-blue-500/10 to-blue-600/10",
    "description": "Nestle Nigeria is a leading company providing excellent career opportunities.",
    "industry": "Various",
    "size": "Multiple employees",
    "website": "https://nestlenigeria.com",
    "founded": "N/A",
    "specialties": [],
    "jobCount": 7
  },
  {
    "id": "gtbank",
    "name": "GTBank",
    "logo": "/images/company-logos/gtbank.svg",
    "location": "Nigeria",
    "gradient": "from-blue-500/10 to-blue-600/10",
    "description": "GTBank is a leading company providing excellent career opportunities.",
    "industry": "Various",
    "size": "Multiple employees",
    "website": "https://gtbank.com",
    "founded": "N/A",
    "specialties": [],
    "jobCount": 7
  },
  {
    "id": "amazon-south-africa",
    "name": "Amazon South Africa",
    "logo": "/images/company-logos/amazon-south-africa.svg",
    "location": "South Africa",
    "gradient": "from-blue-500/10 to-blue-600/10",
    "description": "Amazon South Africa is a leading company providing excellent career opportunities.",
    "industry": "Various",
    "size": "Multiple employees",
    "website": "https://amazonsouthafrica.com",
    "founded": "N/A",
    "specialties": [],
    "jobCount": 6
  },
  {
    "id": "deloitte",
    "name": "Deloitte",
    "logo": "/images/company-logos/deloitte.svg",
    "location": "South Africa",
    "gradient": "from-blue-500/10 to-blue-600/10",
    "description": "Deloitte is a leading company providing excellent career opportunities.",
    "industry": "Various",
    "size": "Multiple employees",
    "website": "https://deloitte.com",
    "founded": "N/A",
    "specialties": [],
    "jobCount": 6
  },
  {
    "id": "jumia",
    "name": "Jumia",
    "logo": "/images/company-logos/jumia.svg",
    "location": "Nigeria",
    "gradient": "from-blue-500/10 to-blue-600/10",
    "description": "Jumia is a leading company providing excellent career opportunities.",
    "industry": "Various",
    "size": "Multiple employees",
    "website": "https://jumia.com",
    "founded": "N/A",
    "specialties": [],
    "jobCount": 6
  },
  {
    "id": "dangote-group",
    "name": "Dangote Group",
    "logo": "/images/company-logos/dangote-group.svg",
    "location": "Nigeria",
    "gradient": "from-blue-500/10 to-blue-600/10",
    "description": "Dangote Group is a leading company providing excellent career opportunities.",
    "industry": "Various",
    "size": "Multiple employees",
    "website": "https://dangotegroup.com",
    "founded": "N/A",
    "specialties": [],
    "jobCount": 6
  },
  {
    "id": "sanlam",
    "name": "Sanlam",
    "logo": "/images/company-logos/sanlam.svg",
    "location": "South Africa",
    "gradient": "from-blue-500/10 to-blue-600/10",
    "description": "Sanlam is a leading company providing excellent career opportunities.",
    "industry": "Various",
    "size": "Multiple employees",
    "website": "https://sanlam.com",
    "founded": "N/A",
    "specialties": [],
    "jobCount": 5
  },
  {
    "id": "absa",
    "name": "Absa",
    "logo": "/images/company-logos/absa.svg",
    "location": "South Africa",
    "gradient": "from-blue-500/10 to-blue-600/10",
    "description": "Absa is a leading company providing excellent career opportunities.",
    "industry": "Various",
    "size": "Multiple employees",
    "website": "https://absa.com",
    "founded": "N/A",
    "specialties": [],
    "jobCount": 5
  },
  {
    "id": "microsoft-south-africa",
    "name": "Microsoft South Africa",
    "logo": "/images/company-logos/microsoft-south-africa.svg",
    "location": "South Africa",
    "gradient": "from-blue-500/10 to-blue-600/10",
    "description": "Microsoft South Africa is a leading company providing excellent career opportunities.",
    "industry": "Various",
    "size": "Multiple employees",
    "website": "https://microsoftsouthafrica.com",
    "founded": "N/A",
    "specialties": [],
    "jobCount": 5
  },
  {
    "id": "shoprite",
    "name": "Shoprite",
    "logo": "/images/company-logos/shoprite.svg",
    "location": "South Africa",
    "gradient": "from-blue-500/10 to-blue-600/10",
    "description": "Shoprite is a leading company providing excellent career opportunities.",
    "industry": "Various",
    "size": "Multiple employees",
    "website": "https://shoprite.com",
    "founded": "N/A",
    "specialties": [],
    "jobCount": 5
  },
  {
    "id": "ibm-south-africa",
    "name": "IBM South Africa",
    "logo": "/images/company-logos/ibm-south-africa.svg",
    "location": "South Africa",
    "gradient": "from-blue-500/10 to-blue-600/10",
    "description": "IBM South Africa is a leading company providing excellent career opportunities.",
    "industry": "Various",
    "size": "Multiple employees",
    "website": "https://ibmsouthafrica.com",
    "founded": "N/A",
    "specialties": [],
    "jobCount": 5
  },
  {
    "id": "9mobile",
    "name": "9mobile",
    "logo": "/images/company-logos/9mobile.svg",
    "location": "Nigeria",
    "gradient": "from-blue-500/10 to-blue-600/10",
    "description": "9mobile is a leading company providing excellent career opportunities.",
    "industry": "Various",
    "size": "Multiple employees",
    "website": "https://9mobile.com",
    "founded": "N/A",
    "specialties": [],
    "jobCount": 5
  },
  {
    "id": "carbon",
    "name": "Carbon",
    "logo": "/images/company-logos/carbon.svg",
    "location": "Nigeria",
    "gradient": "from-blue-500/10 to-blue-600/10",
    "description": "Carbon is a leading company providing excellent career opportunities.",
    "industry": "Various",
    "size": "Multiple employees",
    "website": "https://carbon.com",
    "founded": "N/A",
    "specialties": [],
    "jobCount": 5
  },
  {
    "id": "tfg",
    "name": "TFG",
    "logo": "/images/company-logos/tfg.svg",
    "location": "South Africa",
    "gradient": "from-blue-500/10 to-blue-600/10",
    "description": "TFG is a leading company providing excellent career opportunities.",
    "industry": "Various",
    "size": "Multiple employees",
    "website": "https://tfg.com",
    "founded": "N/A",
    "specialties": [],
    "jobCount": 4
  },
  {
    "id": "woolworths",
    "name": "Woolworths",
    "logo": "/images/company-logos/woolworths.svg",
    "location": "South Africa",
    "gradient": "from-blue-500/10 to-blue-600/10",
    "description": "Woolworths is a leading company providing excellent career opportunities.",
    "industry": "Various",
    "size": "Multiple employees",
    "website": "https://woolworths.com",
    "founded": "N/A",
    "specialties": [],
    "jobCount": 4
  },
  {
    "id": "accenture",
    "name": "Accenture",
    "logo": "/images/company-logos/accenture.svg",
    "location": "South Africa",
    "gradient": "from-blue-500/10 to-blue-600/10",
    "description": "Accenture is a leading company providing excellent career opportunities.",
    "industry": "Various",
    "size": "Multiple employees",
    "website": "https://accenture.com",
    "founded": "N/A",
    "specialties": [],
    "jobCount": 4
  },
  {
    "id": "old-mutual",
    "name": "Old Mutual",
    "logo": "/images/company-logos/old-mutual.svg",
    "location": "South Africa",
    "gradient": "from-blue-500/10 to-blue-600/10",
    "description": "Old Mutual is a leading company providing excellent career opportunities.",
    "industry": "Various",
    "size": "Multiple employees",
    "website": "https://oldmutual.com",
    "founded": "N/A",
    "specialties": [],
    "jobCount": 4
  },
  {
    "id": "google-south-africa",
    "name": "Google South Africa",
    "logo": "/images/company-logos/google-south-africa.svg",
    "location": "South Africa",
    "gradient": "from-blue-500/10 to-blue-600/10",
    "description": "Google South Africa is a leading company providing excellent career opportunities.",
    "industry": "Various",
    "size": "Multiple employees",
    "website": "https://googlesouthafrica.com",
    "founded": "N/A",
    "specialties": [],
    "jobCount": 4
  },
  {
    "id": "standard-bank",
    "name": "Standard Bank",
    "logo": "/images/company-logos/standard-bank.svg",
    "location": "South Africa",
    "gradient": "from-blue-500/10 to-blue-600/10",
    "description": "Standard Bank is a leading company providing excellent career opportunities.",
    "industry": "Various",
    "size": "Multiple employees",
    "website": "https://standardbank.com",
    "founded": "N/A",
    "specialties": [],
    "jobCount": 4
  },
  {
    "id": "mtn",
    "name": "MTN",
    "logo": "/images/company-logos/mtn.svg",
    "location": "South Africa",
    "gradient": "from-blue-500/10 to-blue-600/10",
    "description": "MTN is a leading company providing excellent career opportunities.",
    "industry": "Various",
    "size": "Multiple employees",
    "website": "https://mtn.com",
    "founded": "N/A",
    "specialties": [],
    "jobCount": 4
  },
  {
    "id": "pwc",
    "name": "PwC",
    "logo": "/images/company-logos/pwc.svg",
    "location": "South Africa",
    "gradient": "from-blue-500/10 to-blue-600/10",
    "description": "PwC is a leading company providing excellent career opportunities.",
    "industry": "Various",
    "size": "Multiple employees",
    "website": "https://pwc.com",
    "founded": "N/A",
    "specialties": [],
    "jobCount": 4
  },
  {
    "id": "mr-price-group",
    "name": "Mr Price Group",
    "logo": "/images/company-logos/mr-price-group.svg",
    "location": "South Africa",
    "gradient": "from-blue-500/10 to-blue-600/10",
    "description": "Mr Price Group is a leading company providing excellent career opportunities.",
    "industry": "Various",
    "size": "Multiple employees",
    "website": "https://mrpricegroup.com",
    "founded": "N/A",
    "specialties": [],
    "jobCount": 4
  },
  {
    "id": "flour-mills",
    "name": "Flour Mills",
    "logo": "/images/company-logos/flour-mills.svg",
    "location": "Nigeria",
    "gradient": "from-blue-500/10 to-blue-600/10",
    "description": "Flour Mills is a leading company providing excellent career opportunities.",
    "industry": "Various",
    "size": "Multiple employees",
    "website": "https://flourmills.com",
    "founded": "N/A",
    "specialties": [],
    "jobCount": 4
  },
  {
    "id": "honeywell",
    "name": "Honeywell",
    "logo": "/images/company-logos/honeywell.svg",
    "location": "Nigeria",
    "gradient": "from-blue-500/10 to-blue-600/10",
    "description": "Honeywell is a leading company providing excellent career opportunities.",
    "industry": "Various",
    "size": "Multiple employees",
    "website": "https://honeywell.com",
    "founded": "N/A",
    "specialties": [],
    "jobCount": 4
  },
  {
    "id": "unilever-nigeria",
    "name": "Unilever Nigeria",
    "logo": "/images/company-logos/unilever-nigeria.svg",
    "location": "Nigeria",
    "gradient": "from-blue-500/10 to-blue-600/10",
    "description": "Unilever Nigeria is a leading company providing excellent career opportunities.",
    "industry": "Various",
    "size": "Multiple employees",
    "website": "https://unilevernigeria.com",
    "founded": "N/A",
    "specialties": [],
    "jobCount": 4
  },
  {
    "id": "airtel-nigeria",
    "name": "Airtel Nigeria",
    "logo": "/images/company-logos/airtel-nigeria.svg",
    "location": "Nigeria",
    "gradient": "from-blue-500/10 to-blue-600/10",
    "description": "Airtel Nigeria is a leading company providing excellent career opportunities.",
    "industry": "Various",
    "size": "Multiple employees",
    "website": "https://airtelnigeria.com",
    "founded": "N/A",
    "specialties": [],
    "jobCount": 4
  },
  {
    "id": "globacom",
    "name": "Globacom",
    "logo": "/images/company-logos/globacom.svg",
    "location": "Nigeria",
    "gradient": "from-blue-500/10 to-blue-600/10",
    "description": "Globacom is a leading company providing excellent career opportunities.",
    "industry": "Various",
    "size": "Multiple employees",
    "website": "https://globacom.com",
    "founded": "N/A",
    "specialties": [],
    "jobCount": 4
  },
  {
    "id": "access-bank",
    "name": "Access Bank",
    "logo": "/images/company-logos/access-bank.svg",
    "location": "Nigeria",
    "gradient": "from-blue-500/10 to-blue-600/10",
    "description": "Access Bank is a leading company providing excellent career opportunities.",
    "industry": "Various",
    "size": "Multiple employees",
    "website": "https://accessbank.com",
    "founded": "N/A",
    "specialties": [],
    "jobCount": 4
  },
  {
    "id": "ey",
    "name": "EY",
    "logo": "/images/company-logos/ey.svg",
    "location": "South Africa",
    "gradient": "from-blue-500/10 to-blue-600/10",
    "description": "EY is a leading company providing excellent career opportunities.",
    "industry": "Various",
    "size": "Multiple employees",
    "website": "https://ey.com",
    "founded": "N/A",
    "specialties": [],
    "jobCount": 3
  },
  {
    "id": "kpmg",
    "name": "KPMG",
    "logo": "/images/company-logos/kpmg.svg",
    "location": "South Africa",
    "gradient": "from-blue-500/10 to-blue-600/10",
    "description": "KPMG is a leading company providing excellent career opportunities.",
    "industry": "Various",
    "size": "Multiple employees",
    "website": "https://kpmg.com",
    "founded": "N/A",
    "specialties": [],
    "jobCount": 3
  },
  {
    "id": "discovery-limited",
    "name": "Discovery Limited",
    "logo": "/images/company-logos/discovery-limited.svg",
    "location": "South Africa",
    "gradient": "from-blue-500/10 to-blue-600/10",
    "description": "Discovery Limited is a leading company providing excellent career opportunities.",
    "industry": "Various",
    "size": "Multiple employees",
    "website": "https://discoverylimited.com",
    "founded": "N/A",
    "specialties": [],
    "jobCount": 3
  },
  {
    "id": "vodacom",
    "name": "Vodacom",
    "logo": "/images/company-logos/vodacom.svg",
    "location": "South Africa",
    "gradient": "from-blue-500/10 to-blue-600/10",
    "description": "Vodacom is a leading company providing excellent career opportunities.",
    "industry": "Various",
    "size": "Multiple employees",
    "website": "https://vodacom.com",
    "founded": "N/A",
    "specialties": [],
    "jobCount": 3
  },
  {
    "id": "fnb",
    "name": "FNB",
    "logo": "/images/company-logos/fnb.svg",
    "location": "South Africa",
    "gradient": "from-blue-500/10 to-blue-600/10",
    "description": "FNB is a leading company providing excellent career opportunities.",
    "industry": "Various",
    "size": "Multiple employees",
    "website": "https://fnb.com",
    "founded": "N/A",
    "specialties": [],
    "jobCount": 3
  },
  {
    "id": "cowrywise",
    "name": "Cowrywise",
    "logo": "/images/company-logos/cowrywise.svg",
    "location": "Nigeria",
    "gradient": "from-blue-500/10 to-blue-600/10",
    "description": "Cowrywise is a leading company providing excellent career opportunities.",
    "industry": "Various",
    "size": "Multiple employees",
    "website": "https://cowrywise.com",
    "founded": "N/A",
    "specialties": [],
    "jobCount": 3
  },
  {
    "id": "interswitch",
    "name": "Interswitch",
    "logo": "/images/company-logos/interswitch.svg",
    "location": "Nigeria",
    "gradient": "from-blue-500/10 to-blue-600/10",
    "description": "Interswitch is a leading company providing excellent career opportunities.",
    "industry": "Various",
    "size": "Multiple employees",
    "website": "https://interswitch.com",
    "founded": "N/A",
    "specialties": [],
    "jobCount": 3
  },
  {
    "id": "nedbank",
    "name": "Nedbank",
    "logo": "/images/company-logos/nedbank.svg",
    "location": "South Africa",
    "gradient": "from-blue-500/10 to-blue-600/10",
    "description": "Nedbank is a leading company providing excellent career opportunities.",
    "industry": "Various",
    "size": "Multiple employees",
    "website": "https://nedbank.com",
    "founded": "N/A",
    "specialties": [],
    "jobCount": 2
  },
  {
    "id": "media24",
    "name": "Media24",
    "logo": "/images/company-logos/media24.svg",
    "location": "South Africa",
    "gradient": "from-blue-500/10 to-blue-600/10",
    "description": "Media24 is a leading company providing excellent career opportunities.",
    "industry": "Various",
    "size": "Multiple employees",
    "website": "https://media24.com",
    "founded": "N/A",
    "specialties": [],
    "jobCount": 2
  },
  {
    "id": "takealot",
    "name": "Takealot",
    "logo": "/images/company-logos/takealot.svg",
    "location": "South Africa",
    "gradient": "from-blue-500/10 to-blue-600/10",
    "description": "Takealot is a leading company providing excellent career opportunities.",
    "industry": "Various",
    "size": "Multiple employees",
    "website": "https://takealot.com",
    "founded": "N/A",
    "specialties": [],
    "jobCount": 2
  },
  {
    "id": "naspers",
    "name": "Naspers",
    "logo": "/images/company-logos/naspers.svg",
    "location": "South Africa",
    "gradient": "from-blue-500/10 to-blue-600/10",
    "description": "Naspers is a leading company providing excellent career opportunities.",
    "industry": "Various",
    "size": "Multiple employees",
    "website": "https://naspers.com",
    "founded": "N/A",
    "specialties": [],
    "jobCount": 2
  },
  {
    "id": "paystack",
    "name": "Paystack",
    "logo": "/images/company-logos/paystack.svg",
    "location": "Nigeria",
    "gradient": "from-blue-500/10 to-blue-600/10",
    "description": "Paystack is a leading company providing excellent career opportunities.",
    "industry": "Various",
    "size": "Multiple employees",
    "website": "https://paystack.com",
    "founded": "N/A",
    "specialties": [],
    "jobCount": 2
  },
  {
    "id": "bua-group",
    "name": "BUA Group",
    "logo": "/images/company-logos/bua-group.svg",
    "location": "Nigeria",
    "gradient": "from-blue-500/10 to-blue-600/10",
    "description": "BUA Group is a leading company providing excellent career opportunities.",
    "industry": "Various",
    "size": "Multiple employees",
    "website": "https://buagroup.com",
    "founded": "N/A",
    "specialties": [],
    "jobCount": 2
  },
  {
    "id": "piggyvest",
    "name": "PiggyVest",
    "logo": "/images/company-logos/piggyvest.svg",
    "location": "Nigeria",
    "gradient": "from-blue-500/10 to-blue-600/10",
    "description": "PiggyVest is a leading company providing excellent career opportunities.",
    "industry": "Various",
    "size": "Multiple employees",
    "website": "https://piggyvest.com",
    "founded": "N/A",
    "specialties": [],
    "jobCount": 2
  },
  {
    "id": "mtn-nigeria",
    "name": "MTN Nigeria",
    "logo": "/images/company-logos/mtn-nigeria.svg",
    "location": "Nigeria",
    "gradient": "from-blue-500/10 to-blue-600/10",
    "description": "MTN Nigeria is a leading company providing excellent career opportunities.",
    "industry": "Various",
    "size": "Multiple employees",
    "website": "https://mtnnigeria.com",
    "founded": "N/A",
    "specialties": [],
    "jobCount": 2
  },
  {
    "id": "flutterwave",
    "name": "Flutterwave",
    "logo": "/images/company-logos/flutterwave.svg",
    "location": "Nigeria",
    "gradient": "from-blue-500/10 to-blue-600/10",
    "description": "Flutterwave is a leading company providing excellent career opportunities.",
    "industry": "Various",
    "size": "Multiple employees",
    "website": "https://flutterwave.com",
    "founded": "N/A",
    "specialties": [],
    "jobCount": 2
  },
  {
    "id": "kuda-bank",
    "name": "Kuda Bank",
    "logo": "/images/company-logos/kuda-bank.svg",
    "location": "Nigeria",
    "gradient": "from-blue-500/10 to-blue-600/10",
    "description": "Kuda Bank is a leading company providing excellent career opportunities.",
    "industry": "Various",
    "size": "Multiple employees",
    "website": "https://kudabank.com",
    "founded": "N/A",
    "specialties": [],
    "jobCount": 2
  },
  {
    "id": "bolt",
    "name": "Bolt",
    "logo": "/images/company-logos/bolt.svg",
    "location": "Nigeria",
    "gradient": "from-blue-500/10 to-blue-600/10",
    "description": "Bolt is a leading company providing excellent career opportunities.",
    "industry": "Various",
    "size": "Multiple employees",
    "website": "https://bolt.com",
    "founded": "N/A",
    "specialties": [],
    "jobCount": 2
  },
  {
    "id": "renmoney",
    "name": "Renmoney",
    "logo": "/images/company-logos/renmoney.svg",
    "location": "Nigeria",
    "gradient": "from-blue-500/10 to-blue-600/10",
    "description": "Renmoney is a leading company providing excellent career opportunities.",
    "industry": "Various",
    "size": "Multiple employees",
    "website": "https://renmoney.com",
    "founded": "N/A",
    "specialties": [],
    "jobCount": 2
  },
  {
    "id": "momentum-metropolitan",
    "name": "Momentum Metropolitan",
    "logo": "/images/company-logos/momentum-metropolitan.svg",
    "location": "South Africa",
    "gradient": "from-blue-500/10 to-blue-600/10",
    "description": "Momentum Metropolitan is a leading company providing excellent career opportunities.",
    "industry": "Various",
    "size": "Multiple employees",
    "website": "https://momentummetropolitan.com",
    "founded": "N/A",
    "specialties": [],
    "jobCount": 1
  },
  {
    "id": "pick-n-pay",
    "name": "Pick n Pay",
    "logo": "/images/company-logos/pick-n-pay.svg",
    "location": "South Africa",
    "gradient": "from-blue-500/10 to-blue-600/10",
    "description": "Pick n Pay is a leading company providing excellent career opportunities.",
    "industry": "Various",
    "size": "Multiple employees",
    "website": "https://picknpay.com",
    "founded": "N/A",
    "specialties": [],
    "jobCount": 1
  },
  {
    "id": "capitec-bank",
    "name": "Capitec Bank",
    "logo": "/images/company-logos/capitec-bank.svg",
    "location": "South Africa",
    "gradient": "from-blue-500/10 to-blue-600/10",
    "description": "Capitec Bank is a leading company providing excellent career opportunities.",
    "industry": "Various",
    "size": "Multiple employees",
    "website": "https://capitecbank.com",
    "founded": "N/A",
    "specialties": [],
    "jobCount": 1
  },
  {
    "id": "multichoice",
    "name": "MultiChoice",
    "logo": "/images/company-logos/multichoice.svg",
    "location": "South Africa",
    "gradient": "from-blue-500/10 to-blue-600/10",
    "description": "MultiChoice is a leading company providing excellent career opportunities.",
    "industry": "Various",
    "size": "Multiple employees",
    "website": "https://multichoice.com",
    "founded": "N/A",
    "specialties": [],
    "jobCount": 1
  },
  {
    "id": "andela",
    "name": "Andela",
    "logo": "/images/company-logos/andela.svg",
    "location": "Nigeria",
    "gradient": "from-blue-500/10 to-blue-600/10",
    "description": "Andela is a leading company providing excellent career opportunities.",
    "industry": "Various",
    "size": "Multiple employees",
    "website": "https://andela.com",
    "founded": "N/A",
    "specialties": [],
    "jobCount": 1
  }
]